davodtime/__init__.py
davodtime/main.py
davodtime-0.1.2.dist-info/LICENSE
davodtime-0.1.2.dist-info/METADATA
davodtime-0.1.2.dist-info/WHEEL
davodtime-0.1.2.dist-info/entry_points.txt
davodtime-0.1.2.dist-info/top_level.txt
davodtime-0.1.2.dist-info/RECORD
