Metadata-Version: 2.1
Name: davodtime
Version: 0.1.2
Summary: A command line tool to display time in various formats.
Home-page: https://github.com/extratone/davodtimecli
Author: David Blue
Author-email: davidblue@extratone.com
Classifier: Programming Language :: Python :: 3
Classifier: License :: OSI Approved :: MIT License
Classifier: Operating System :: OS Independent
Requires-Python: >=3.6
License-File: LICENSE
Requires-Dist: pytz
